riptide_cli/__init__.py
riptide_cli/__main__.py
riptide_cli/click.py
riptide_cli/helpers.py
riptide_cli/hook.py
riptide_cli/lifecycle.py
riptide_cli/loader.py
riptide_cli/py.typed
riptide_cli/self_updater.py
riptide_cli/setup_assistant.py
riptide_cli/shell_integration.py
riptide_cli/command/__init__.py
riptide_cli/command/config.py
riptide_cli/command/constants.py
riptide_cli/command/db.py
riptide_cli/command/hook.py
riptide_cli/command/importt.py
riptide_cli/command/log.py
riptide_cli/command/project.py
riptide_cli/command/projects.py
riptide_cli/shell/riptide.hook.bash
riptide_cli/shell/riptide.hook.common.sh
riptide_cli/shell/riptide.hook.zsh
riptide_cli-0.10.1.data/scripts/riptide.hook.bash
riptide_cli-0.10.1.data/scripts/riptide.hook.common.sh
riptide_cli-0.10.1.data/scripts/riptide.hook.zsh
riptide_cli-0.10.1.dist-info/licenses/LICENSE
riptide_cli-0.10.1.dist-info/METADATA
riptide_cli-0.10.1.dist-info/WHEEL
riptide_cli-0.10.1.dist-info/entry_points.txt
riptide_cli-0.10.1.dist-info/top_level.txt
riptide_cli-0.10.1.dist-info/RECORD
