Metadata-Version: 2.4
Name: riptide-cli
Version: 0.10.1
Summary: Tool to manage development environments for web applications using containers - CLI-Application
Author-email: Marco Köpcke <hello@capypara.de>
License-Expression: MIT
Project-URL: Repository, https://github.com/theCapypara/riptide-cli
Project-URL: Documentation, https://riptide-docs.readthedocs.io
Classifier: Development Status :: 4 - Beta
Classifier: Programming Language :: Python
Classifier: Intended Audience :: Developers
Classifier: Programming Language :: Python :: 3.11
Classifier: Programming Language :: Python :: 3.12
Classifier: Programming Language :: Python :: 3.13
Classifier: Programming Language :: Python :: 3.14
Requires-Python: >=3.11
License-File: LICENSE
Requires-Dist: riptide-lib<0.11,>=0.10
Requires-Dist: Click<9.0,>=8.2
Requires-Dist: rich<15.0,>=14.1
Requires-Dist: click-help-colors>=0.5
Requires-Dist: setproctitle>=1.3.7
Requires-Dist: packaging
Dynamic: license-file
